Workbook

Sheet summary
C1: Gastos individuales de cada uno | E1: Cuánto aportó cada uno a los gastos compartidos | H1: % aportado del total de compartidos | J1: cuánto desembolsó cada uno de su bolsillo | L1: cuánto ingresó cada uno marcado como individual | N1: cuánto ingresó cada uno marcado como compartido | P1: % de ingresos compartidos aportados | S1: cuánto ingresó cada uno total (tanto marcado individual como compartido) | U1: ahorro en el bolsillo x persona (ingresos de una persona - gastos compartidos divididos proporcionalmente - gastos individuales) | W1: ahorro servicios | AA1: cuánto le debe uno a otro para balancear los gastos compartidos mensuales | AC1: neto ahorro hogar
B2: Gastos por mes | C2: gastos (ind) | D2: gastos (ind) | E2: gastos compartidos | F2: gastos compartidos | G2: gastos compartidos | H2: gastos compartidos % | I2: gastos compartidos % | J2: gastos total (comp + ind) | K2: gastos total (comp + ind) | L2: ingresos (ind) | M2: ingresos (ind) | N2: ingresos compartidos | O2: ingresos compartidos | P2: ingresos % | Q2: ingresos % | R2: ingresos compartidos | S2: ingresos total (comp + ind) | T2: ingresos total (comp + ind) | U2: ahorro (comp - ind) | V2: ahorro (comp - ind) | W2: ahorro (compartido) | X2: % ahorro sobre ingreso x persona | Y2: % ahorro sobre ingreso x persona | Z2: % ahorro (compartido) | AA2: saldo
B3: user | C3: user-a | D3: user-b | E3: user-a | F3: user-b | G3: total | H3: user-a | I3: user-b | J3: user-a | K3: user-b | L3: user-a | M3: user-b | N3: user-a | O3: user-b | P3: user-a | Q3: user-b | R3: total | S3: user-a | T3: user-b | U3: user-a | V3: user-b | W3: total | X3: user-a | Y3: user-b | Z3: total | AA3: user-a a user-b | AB3: user-b a user-a
A4: =YEAR(B4) -> 2024 | B4: 45444 | C4: =SUMIFS( expenses_by_installments!$L:$L, expenses_by_installments!$I:$I, "Egreso", expenses_by_installments!$K:$K, C$3, expenses_by_installments!$J:$J, "No", expenses_by_installments!$B:$B, ">="&$B4, expenses_by_installments!$B:$B, "<="&EOMONTH($B4, 0) ) -> 0 | D4: =SUMIFS( expenses_by_installments!$L:$L, expenses_by_installments!$I:$I, "Egreso", expenses_by_installments!$K:$K, D$3, expenses_by_installments!$J:$J, "No", expenses_by_installments!$B:$B, ">="&$B4, expenses_by_installments!$B:$B, "<="&EOMONTH($B4, 0) ) -> 209.03285 | E4: =SUMIFS( expenses_by_installments!$L:$L, expenses_by_installments!$I:$I, "Egreso", expenses_by_installments!$J:$J, "Si", expenses_by_installments!$K:$K, E$3, expenses_by_installments!$B:$B, ">="&$B4, expenses_by_installments!$B:$B, "<="&EOMONTH($B4, 0) ) -> 0 | F4: =SUMIFS( expenses_by_installments!$L:$L, expenses_by_installments!$I:$I, "Egreso", expenses_by_installments!$J:$J, "Si", expenses_by_installments!$K:$K, F$3, expenses_by_installments!$B:$B, ">="&$B4, expenses_by_installments!$B:$B, "<="&EOMONTH($B4, 0) ) -> 795.59854 | G4: =E4+F4 -> 795.59854 | H4: =E4/$G4 -> 0 | I4: =F4/$G4 -> 1 | J4: =E4+C4 -> 0 | K4: =F4+D4 -> 1004.6314 | L4: =SUMIFS( expenses_by_installments!$L:$L, expenses_by_installments!$I:$I, "Ingreso", expenses_by_installments!$K:$K, L$3, expenses_by_installments!$J:$J, "No", expenses_by_installments!$B:$B, ">="&$B4, expenses_by_installments!$B:$B, "<="&EOMONTH($B4, 0) ) -> 0 | M4: =SUMIFS( expenses_by_installments!$L:$L, expenses_by_installments!$I:$I, "Ingreso", expenses_by_installments!$K:$K, M$3, expenses_by_installments!$J:$J, "No", expenses_by_installments!$B:$B, ">="&$B4, expenses_by_installments!$B:$B, "<="&EOMONTH($B4, 0) ) -> 0 | N4: =SUMIFS( expenses_by_installments!$L:$L, expenses_by_installments!$I:$I, "Ingreso", expenses_by_installments!$K:$K, N$3, expenses_by_installments!$J:$J, "Si", expenses_by_installments!$B:$B, ">="&$B4, expenses_by_installments!$B:$B, "<="&EOMONTH($B4, 0) ) -> 0 | O4: 1500 | P4: 0 | Q4: 1 | R4: =N4+O4 -> 1500 | S4: =L4+N4 -> 0 | T4: =M4+O4 -> 1500 | U4: =(S4) - C4 - (G4 * P4) -> 0 | V4: =T4 - D4 - (Q4 * G4) -> 495.36861 | W4: =R4-G4 -> 704.40146 | X4: =U4/S4 -> #DIV/0! | Y4: =V4/T4 -> 0.33024574 | Z4: =W4/R4 -> 0.46960097 | AA4: =MAX(0, (P4 * G4) - E4) -> 0 | AB4: =MAX(0, (Q4 * G4) - F4) -> 0 | AC4: =R4-K4-J4 -> 495.36861
A5: =YEAR(B5) -> 2024 | B5: 45474 | C5: =SUMIFS( expenses_by_installments!$L:$L, expenses_by_installments!$I:$I, "Egreso", expenses_by_installments!$K:$K, C$3, expenses_by_installments!$J:$J, "No", expenses_by_installments!$B:$B, ">="&$B5, expenses_by_installments!$B:$B, "<="&EOMONTH($B5, 0) ) -> 0 | D5: =SUMIFS( expenses_by_installments!$L:$L, expenses_by_installments!$I:$I, "Egreso", expenses_by_installments!$K:$K, D$3, expenses_by_installments!$J:$J, "No", expenses_by_installments!$B:$B, ">="&$B5, expenses_by_installments!$B:$B, "<="&EOMONTH($B5, 0) ) -> 80.946154 | E5: =SUMIFS( expenses_by_installments!$L:$L, expenses_by_installments!$I:$I, "Egreso", expenses_by_installments!$J:$J, "Si", expenses_by_installments!$K:$K, E$3, expenses_by_installments!$B:$B, ">="&$B5, expenses_by_installments!$B:$B, "<="&EOMONTH($B5, 0) ) -> 0 | F5: =SUMIFS( expenses_by_installments!$L:$L, expenses_by_installments!$I:$I, "Egreso", expenses_by_installments!$J:$J, "Si", expenses_by_installments!$K:$K, F$3, expenses_by_installments!$B:$B, ">="&$B5, expenses_by_installments!$B:$B, "<="&EOMONTH($B5, 0) ) -> 967.16154 | G5: =E5+F5 -> 967.16154 | H5: =E5/$G5 -> 0 | I5: =F5/$G5 -> 1 | J5: =E5+C5 -> 0 | K5: =F5+D5 -> 1048.1077 | L5: =SUMIFS( expenses_by_installments!$L:$L, expenses_by_installments!$I:$I, "Ingreso", expenses_by_installments!$K:$K, L$3, expenses_by_installments!$J:$J, "No", expenses_by_installments!$B:$B, ">="&$B5, expenses_by_installments!$B:$B, "<="&EOMONTH($B5, 0) ) -> 0 | M5: =SUMIFS( expenses_by_installments!$L:$L, expenses_by_installments!$I:$I, "Ingreso", expenses_by_installments!$K:$K, M$3, expenses_by_installments!$J:$J, "No", expenses_by_installments!$B:$B, ">="&$B5, expenses_by_installments!$B:$B, "<="&EOMONTH($B5, 0) ) -> 0 | N5: =SUMIFS( expenses_by_installments!$L:$L, expenses_by_installments!$I:$I, "Ingreso", expenses_by_installments!$K:$K, N$3, expenses_by_installments!$J:$J, "Si", expenses_by_installments!$B:$B, ">="&$B5, expenses_by_installments!$B:$B, "<="&EOMONTH($B5, 0) ) -> 0 | O5: 1500 | P5: 0 | Q5: 1 | R5: =N5+O5 -> 1500 | S5: =L5+N5 -> 0 | T5: =M5+O5 -> 1500 | U5: =(S5) - C5 - (G5 * P5) -> 0 | V5: =T5 - D5 - (Q5 * G5) -> 451.89231 | W5: =R5-G5 -> 532.83846 | X5: =U5/S5 -> #DIV/0! | Y5: =V5/T5 -> 0.30126154 | Z5: =W5/R5 -> 0.35522564 | AA5: =MAX(0, (P5 * G5) - E5) -> 0 | AB5: =MAX(0, (Q5 * G5) - F5) -> 0 | AC5: =R5-K5-J5 -> 451.89231
A6: =YEAR(B6) -> 2024 | B6: 45505 | C6: =SUMIFS( expenses_by_installments!$L:$L, expenses_by_installments!$I:$I, "Egreso", expenses_by_installments!$K:$K, C$3, expenses_by_installments!$J:$J, "No", expenses_by_installments!$B:$B, ">="&$B6, expenses_by_installments!$B:$B, "<="&EOMONTH($B6, 0) ) -> 0 | D6: =SUMIFS( expenses_by_installments!$L:$L, expenses_by_installments!$I:$I, "Egreso", expenses_by_installments!$K:$K, D$3, expenses_by_installments!$J:$J, "No", expenses_by_installments!$B:$B, ">="&$B6, expenses_by_installments!$B:$B, "<="&EOMONTH($B6, 0) ) -> 66.340081 | E6: =SUMIFS( expenses_by_installments!$L:$L, expenses_by_installments!$I:$I, "Egreso", expenses_by_installments!$J:$J, "Si", expenses_by_installments!$K:$K, E$3, expenses_by_installments!$B:$B, ">="&$B6, expenses_by_installments!$B:$B, "<="&EOMONTH($B6, 0) ) -> 0 | F6: =SUMIFS( expenses_by_installments!$L:$L, expenses_by_installments!$I:$I, "Egreso", expenses_by_installments!$J:$J, "Si", expenses_by_installments!$K:$K, F$3, expenses_by_installments!$B:$B, ">="&$B6, expenses_by_installments!$B:$B, "<="&EOMONTH($B6, 0) ) -> 140.21053 | G6: =E6+F6 -> 140.21053 | H6: =E6/$G6 -> 0 | I6: =F6/$G6 -> 1 | J6: =E6+C6 -> 0 | K6: =F6+D6 -> 206.55061 | L6: =SUMIFS( expenses_by_installments!$L:$L, expenses_by_installments!$I:$I, "Ingreso", expenses_by_installments!$K:$K, L$3, expenses_by_installments!$J:$J, "No", expenses_by_installments!$B:$B, ">="&$B6, expenses_by_installments!$B:$B, "<="&EOMONTH($B6, 0) ) -> 0 | M6: =SUMIFS( expenses_by_installments!$L:$L, expenses_by_installments!$I:$I, "Ingreso", expenses_by_installments!$K:$K, M$3, expenses_by_installments!$J:$J, "No", expenses_by_installments!$B:$B, ">="&$B6, expenses_by_installments!$B:$B, "<="&EOMONTH($B6, 0) ) -> 0 | N6: =SUMIFS( expenses_by_installments!$L:$L, expenses_by_installments!$I:$I, "Ingreso", expenses_by_installments!$K:$K, N$3, expenses_by_installments!$J:$J, "Si", expenses_by_installments!$B:$B, ">="&$B6, expenses_by_installments!$B:$B, "<="&EOMONTH($B6, 0) ) -> 0 | O6: =SUMIFS( expenses_by_installments!$L:$L, expenses_by_installments!$I:$I, "Ingreso", expenses_by_installments!$K:$K, O$3, expenses_by_installments!$J:$J, "Si", expenses_by_installments!$B:$B, ">="&$B6, expenses_by_installments!$B:$B, "<="&EOMONTH($B6, 0) ) -> 0 | P6: 0 | Q6: 1 | R6: =N6+O6 -> 0 | S6: =L6+N6 -> 0 | T6: =M6+O6 -> 0 | U6: =(S6) - C6 - (G6 * P6) -> 0 | V6: =T6 - D6 - (Q6 * G6) -> -206.55061 | W6: =R6-G6 -> -140.21053 | X6: =U6/S6 -> #DIV/0! | Y6: =V6/T6 -> #DIV/0! | Z6: =W6/R6 -> #DIV/0! | AA6: =MAX(0, (P6 * G6) - E6) -> 0 | AB6: =MAX(0, (Q6 * G6) - F6) -> 0 | AC6: =R6-K6-J6 -> -206.55061
A7: =YEAR(B7) -> 2024 | B7: 45536 | C7: =SUMIFS( expenses_by_installments!$L:$L, expenses_by_installments!$I:$I, "Egreso", expenses_by_installments!$K:$K, C$3, expenses_by_installments!$J:$J, "No", expenses_by_installments!$B:$B, ">="&$B7, expenses_by_installments!$B:$B, "<="&EOMONTH($B7, 0) ) -> 0 | D7: =SUMIFS( expenses_by_installments!$L:$L, expenses_by_installments!$I:$I, "Egreso", expenses_by_installments!$K:$K, D$3, expenses_by_installments!$J:$J, "No", expenses_by_installments!$B:$B, ">="&$B7, expenses_by_installments!$B:$B, "<="&EOMONTH($B7, 0) ) -> 45.123967 | E7: =SUMIFS( expenses_by_installments!$L:$L, expenses_by_installments!$I:$I, "Egreso", expenses_by_installments!$J:$J, "Si", expenses_by_installments!$K:$K, E$3, expenses_by_installments!$B:$B, ">="&$B7, expenses_by_installments!$B:$B, "<="&EOMONTH($B7, 0) ) -> 0 | F7: =SUMIFS( expenses_by_installments!$L:$L, expenses_by_installments!$I:$I, "Egreso", expenses_by_installments!$J:$J, "Si", expenses_by_installments!$K:$K, F$3, expenses_by_installments!$B:$B, ">="&$B7, expenses_by_installments!$B:$B, "<="&EOMONTH($B7, 0) ) -> 116.10744 | G7: =E7+F7 -> 116.10744 | H7: =E7/$G7 -> 0 | I7: =F7/$G7 -> 1 | J7: =E7+C7 -> 0 | K7: =F7+D7 -> 161.2314 | L7: =SUMIFS( expenses_by_installments!$L:$L, expenses_by_installments!$I:$I, "Ingreso", expenses_by_installments!$K:$K, L$3, expenses_by_installments!$J:$J, "No", expenses_by_installments!$B:$B, ">="&$B7, expenses_by_installments!$B:$B, "<="&EOMONTH($B7, 0) ) -> 0 | M7: =SUMIFS( expenses_by_installments!$L:$L, expenses_by_installments!$I:$I, "Ingreso", expenses_by_installments!$K:$K, M$3, expenses_by_installments!$J:$J, "No", expenses_by_installments!$B:$B, ">="&$B7, expenses_by_installments!$B:$B, "<="&EOMONTH($B7, 0) ) -> 0 | N7: =SUMIFS( expenses_by_installments!$L:$L, expenses_by_installments!$I:$I, "Ingreso", expenses_by_installments!$K:$K, N$3, expenses_by_installments!$J:$J, "Si", expenses_by_installments!$B:$B, ">="&$B7, expenses_by_installments!$B:$B, "<="&EOMONTH($B7, 0) ) -> 0 | O7: =SUMIFS( expenses_by_installments!$L:$L, expenses_by_installments!$I:$I, "Ingreso", expenses_by_installments!$K:$K, O$3, expenses_by_installments!$J:$J, "Si", expenses_by_installments!$B:$B, ">="&$B7, expenses_by_installments!$B:$B, "<="&EOMONTH($B7, 0) ) -> 0 | P7: 0 | Q7: 1 | R7: =N7+O7 -> 0 | S7: =L7+N7 -> 0 | T7: =M7+O7 -> 0 | U7: =(S7) - C7 - (G7 * P7) -> 0 | V7: =T7 - D7 - (Q7 * G7) -> -161.2314 | W7: =R7-G7 -> -116.10744 | X7: =U7/S7 -> #DIV/0! | Y7: =V7/T7 -> #DIV/0! | Z7: =W7/R7 -> #DIV/0! | AA7: =MAX(0, (P7 * G7) - E7) -> 0 | AB7: =MAX(0, (Q7 * G7) - F7) -> 0 | AC7: =R7-K7-J7 -> -161.2314
A8: =YEAR(B8) -> 2024 | B8: 45566 | C8: =SUMIFS( expenses_by_installments!$L:$L, expenses_by_installments!$I:$I, "Egreso", expenses_by_installments!$K:$K, C$3, expenses_by_installments!$J:$J, "No", expenses_by_installments!$B:$B, ">="&$B8, expenses_by_installments!$B:$B, "<="&EOMONTH($B8, 0) ) -> 0 | D8: =SUMIFS( expenses_by_installments!$L:$L, expenses_by_installments!$I:$I, "Egreso", expenses_by_installments!$K:$K, D$3, expenses_by_installments!$J:$J, "No", expenses_by_installments!$B:$B, ">="&$B8, expenses_by_installments!$B:$B, "<="&EOMONTH($B8, 0) ) -> 47.894737 | E8: =SUMIFS( expenses_by_installments!$L:$L, expenses_by_installments!$I:$I, "Egreso", expenses_by_installments!$J:$J, "Si", expenses_by_installments!$K:$K, E$3, expenses_by_installments!$B:$B, ">="&$B8, expenses_by_installments!$B:$B, "<="&EOMONTH($B8, 0) ) -> 0 | F8: =SUMIFS( expenses_by_installments!$L:$L, expenses_by_installments!$I:$I, "Egreso", expenses_by_installments!$J:$J, "Si", expenses_by_installments!$K:$K, F$3, expenses_by_installments!$B:$B, ">="&$B8, expenses_by_installments!$B:$B, "<="&EOMONTH($B8, 0) ) -> 28.438596 | G8: =E8+F8 -> 28.438596 | H8: =E8/$G8 -> 0 | I8: =F8/$G8 -> 1 | J8: =E8+C8 -> 0 | K8: =F8+D8 -> 76.333333 | L8: =SUMIFS( expenses_by_installments!$L:$L, expenses_by_installments!$I:$I, "Ingreso", expenses_by_installments!$K:$K, L$3, expenses_by_installments!$J:$J, "No", expenses_by_installments!$B:$B, ">="&$B8, expenses_by_installments!$B:$B, "<="&EOMONTH($B8, 0) ) -> 0 | M8: =SUMIFS( expenses_by_installments!$L:$L, expenses_by_installments!$I:$I, "Ingreso", expenses_by_installments!$K:$K, M$3, expenses_by_installments!$J:$J, "No", expenses_by_installments!$B:$B, ">="&$B8, expenses_by_installments!$B:$B, "<="&EOMONTH($B8, 0) ) -> 0 | N8: =SUMIFS( expenses_by_installments!$L:$L, expenses_by_installments!$I:$I, "Ingreso", expenses_by_installments!$K:$K, N$3, expenses_by_installments!$J:$J, "Si", expenses_by_installments!$B:$B, ">="&$B8, expenses_by_installments!$B:$B, "<="&EOMONTH($B8, 0) ) -> 0 | O8: =SUMIFS( expenses_by_installments!$L:$L, expenses_by_installments!$I:$I, "Ingreso", expenses_by_installments!$K:$K, O$3, expenses_by_installments!$J:$J, "Si", expenses_by_installments!$B:$B, ">="&$B8, expenses_by_installments!$B:$B, "<="&EOMONTH($B8, 0) ) -> 0 | P8: 0 | Q8: 1 | R8: =N8+O8 -> 0 | S8: =L8+N8 -> 0 | T8: =M8+O8 -> 0 | U8: =(S8) - C8 - (G8 * P8) -> 0 | V8: =T8 - D8 - (Q8 * G8) -> -76.333333 | W8: =R8-G8 -> -28.438596 | X8: =U8/S8 -> #DIV/0! | Y8: =V8/T8 -> #DIV/0! | Z8: =W8/R8 -> #DIV/0! | AA8: =MAX(0, (P8 * G8) - E8) -> 0 | AB8: =MAX(0, (Q8 * G8) - F8) -> 0 | AC8: =R8-K8-J8 -> -76.333333
A9: =YEAR(B9) -> 2024 | B9: 45597 | C9: =SUMIFS( expenses_by_installments!$L:$L, expenses_by_installments!$I:$I, "Egreso", expenses_by_installments!$K:$K, C$3, expenses_by_installments!$J:$J, "No", expenses_by_installments!$B:$B, ">="&$B8, expenses_by_installments!$B:$B, "<="&EOMONTH($B8, 0) ) -> 0 | D9: =SUMIFS( expenses_by_installments!$L:$L, expenses_by_installments!$I:$I, "Egreso", expenses_by_installments!$K:$K, D$3, expenses_by_installments!$J:$J, "No", expenses_by_installments!$B:$B, ">="&$B8, expenses_by_installments!$B:$B, "<="&EOMONTH($B8, 0) ) -> 47.894737 | E9: =SUMIFS( expenses_by_installments!$L:$L, expenses_by_installments!$I:$I, "Egreso", expenses_by_installments!$J:$J, "Si", expenses_by_installments!$K:$K, E$3, expenses_by_installments!$B:$B, ">="&$B8, expenses_by_installments!$B:$B, "<="&EOMONTH($B8, 0) ) -> 0 | F9: =SUMIFS( expenses_by_installments!$L:$L, expenses_by_installments!$I:$I, "Egreso", expenses_by_installments!$J:$J, "Si", expenses_by_installments!$K:$K, F$3, expenses_by_installments!$B:$B, ">="&$B8, expenses_by_installments!$B:$B, "<="&EOMONTH($B8, 0) ) -> 28.438596 | G9: =E8+F8 -> 28.438596 | H9: =E8/$G8 -> 0 | I9: =F8/$G8 -> 1 | J9: =E8+C8 -> 0 | K9: =F8+D8 -> 76.333333 | L9: =SUMIFS( expenses_by_installments!$L:$L, expenses_by_installments!$I:$I, "Ingreso", expenses_by_installments!$K:$K, L$3, expenses_by_installments!$J:$J, "No", expenses_by_installments!$B:$B, ">="&$B8, expenses_by_installments!$B:$B, "<="&EOMONTH($B8, 0) ) -> 0 | M9: =SUMIFS( expenses_by_installments!$L:$L, expenses_by_installments!$I:$I, "Ingreso", expenses_by_installments!$K:$K, M$3, expenses_by_installments!$J:$J, "No", expenses_by_installments!$B:$B, ">="&$B8, expenses_by_installments!$B:$B, "<="&EOMONTH($B8, 0) ) -> 0 | N9: =SUMIFS( expenses_by_installments!$L:$L, expenses_by_installments!$I:$I, "Ingreso", expenses_by_installments!$K:$K, N$3, expenses_by_installments!$J:$J, "Si", expenses_by_installments!$B:$B, ">="&$B8, expenses_by_installments!$B:$B, "<="&EOMONTH($B8, 0) ) -> 0 | O9: =SUMIFS( expenses_by_installments!$L:$L, expenses_by_installments!$I:$I, "Ingreso", expenses_by_installments!$K:$K, O$3, expenses_by_installments!$J:$J, "Si", expenses_by_installments!$B:$B, ">="&$B8, expenses_by_installments!$B:$B, "<="&EOMONTH($B8, 0) ) -> 0 | P9: 0 | Q9: 0 | R9: =N8+O8 -> 0 | S9: =L8+N8 -> 0 | T9: =M8+O8 -> 0 | U9: =(S8) - C8 - (G8 * P8) -> 0 | V9: =T8 - D8 - (Q8 * G8) -> -76.333333 | W9: =R8-G8 -> -28.438596 | X9: =U8/S8 -> #DIV/0! | Y9: =V8/T8 -> #DIV/0! | Z9: =W8/R8 -> #DIV/0! | AA9: =MAX(0, (P8 * G8) - E8) -> 0 | AB9: =MAX(0, (Q8 * G8) - F8) -> 0 | AC9: =R8-K8-J8 -> -76.333333
A10: =YEAR(B10) -> 2024 | B10: 45627 | C10: =SUMIFS( expenses_by_installments!$L:$L, expenses_by_installments!$I:$I, "Egreso", expenses_by_installments!$K:$K, C$3, expenses_by_installments!$J:$J, "No", expenses_by_installments!$B:$B, ">="&$B8, expenses_by_installments!$B:$B, "<="&EOMONTH($B8, 0) ) -> 0 | D10: =SUMIFS( expenses_by_installments!$L:$L, expenses_by_installments!$I:$I, "Egreso", expenses_by_installments!$K:$K, D$3, expenses_by_installments!$J:$J, "No", expenses_by_installments!$B:$B, ">="&$B8, expenses_by_installments!$B:$B, "<="&EOMONTH($B8, 0) ) -> 47.894737 | E10: =SUMIFS( expenses_by_installments!$L:$L, expenses_by_installments!$I:$I, "Egreso", expenses_by_installments!$J:$J, "Si", expenses_by_installments!$K:$K, E$3, expenses_by_installments!$B:$B, ">="&$B8, expenses_by_installments!$B:$B, "<="&EOMONTH($B8, 0) ) -> 0 | F10: =SUMIFS( expenses_by_installments!$L:$L, expenses_by_installments!$I:$I, "Egreso", expenses_by_installments!$J:$J, "Si", expenses_by_installments!$K:$K, F$3, expenses_by_installments!$B:$B, ">="&$B8, expenses_by_installments!$B:$B, "<="&EOMONTH($B8, 0) ) -> 28.438596 | G10: =E8+F8 -> 28.438596 | H10: =E8/$G8 -> 0 | I10: =F8/$G8 -> 1 | J10: =E8+C8 -> 0 | K10: =F8+D8 -> 76.333333 | L10: =SUMIFS( expenses_by_installments!$L:$L, expenses_by_installments!$I:$I, "Ingreso", expenses_by_installments!$K:$K, L$3, expenses_by_installments!$J:$J, "No", expenses_by_installments!$B:$B, ">="&$B8, expenses_by_installments!$B:$B, "<="&EOMONTH($B8, 0) ) -> 0 | M10: =SUMIFS( expenses_by_installments!$L:$L, expenses_by_installments!$I:$I, "Ingreso", expenses_by_installments!$K:$K, M$3, expenses_by_installments!$J:$J, "No", expenses_by_installments!$B:$B, ">="&$B8, expenses_by_installments!$B:$B, "<="&EOMONTH($B8, 0) ) -> 0 | N10: =SUMIFS( expenses_by_installments!$L:$L, expenses_by_installments!$I:$I, "Ingreso", expenses_by_installments!$K:$K, N$3, expenses_by_installments!$J:$J, "Si", expenses_by_installments!$B:$B, ">="&$B8, expenses_by_installments!$B:$B, "<="&EOMONTH($B8, 0) ) -> 0 | O10: =SUMIFS( expenses_by_installments!$L:$L, expenses_by_installments!$I:$I, "Ingreso", expenses_by_installments!$K:$K, O$3, expenses_by_installments!$J:$J, "Si", expenses_by_installments!$B:$B, ">="&$B8, expenses_by_installments!$B:$B, "<="&EOMONTH($B8, 0) ) -> 0 | P10: 0 | Q10: 0 | R10: =N8+O8 -> 0 | S10: =L8+N8 -> 0 | T10: =M8+O8 -> 0 | U10: =(S8) - C8 - (G8 * P8) -> 0 | V10: =T8 - D8 - (Q8 * G8) -> -76.333333 | W10: =R8-G8 -> -28.438596 | X10: =U8/S8 -> #DIV/0! | Y10: =V8/T8 -> #DIV/0! | Z10: =W8/R8 -> #DIV/0! | AA10: =MAX(0, (P8 * G8) - E8) -> 0 | AB10: =MAX(0, (Q8 * G8) - F8) -> 0 | AC10: =R8-K8-J8 -> -76.333333

Sheet summary_by_categories
A1: Categoría | B1: Tipo | C1: user | D1: compartido | E1: período | F1: monto
A2: =IFERROR(__xludf.DUMMYFUNCTION("LET( datos_gastos, expenses_by_installments!A2:N23671, cat_maestra, 'expenses-categories'!B2:D23671, col_cat_gasto, INDEX(datos_gastos,,4), col_compartido_gasto, INDEX(datos_gastos,,10), col_user_gasto, INDEX(datos_gastos,,11), col"&"_periodo_gasto, INDEX(datos_gastos,,14), col_monto_gasto, INDEX(datos_gastos,,12), universo, UNIQUE(FILTER(HSTACK(col_cat_gasto, col_periodo_gasto, col_user_gasto, col_compartido_gasto), (col_cat_gasto<>""""))), resumen, BYROW(universo, LAMBDA"&"(fila, LET( cat_nom, INDEX(fila, 1, 1), p_orig, INDEX(fila, 1, 2), usuario, INDEX(fila, 1, 3), comp, INDEX(fila, 1, 4), periodo_iso, RIGHT(p_orig, 4) & ""-"" & LEFT(p_orig, 2), "&" tipo, XLOOKUP(cat_nom, INDEX(cat_maestra,,1), INDEX(cat_maestra,,3), ""Gasto""), monto, SUMIFS(col_monto_gasto, col_cat_gasto, cat_nom, col_periodo_gasto, p_orig, col_user_gasto, usuario, col_compartido_gasto, comp), HSTACK(cat_"&"nom, tipo, usuario, comp, periodo_iso, monto) ) )), SORT(FILTER(resumen, (INDEX(resumen,,6)>0)), 5, TRUE) )"),"servicios") -> servicios | B2: =IFERROR(__xludf.DUMMYFUNCTION("""COMPUTED_VALUE"""),"Gasto") -> Gasto | C2: =IFERROR(__xludf.DUMMYFUNCTION("""COMPUTED_VALUE"""),"user-b") -> user-b | D2: =IFERROR(__xludf.DUMMYFUNCTION("""COMPUTED_VALUE"""),"Si") -> Si | E2: =IFERROR(__xludf.DUMMYFUNCTION("""COMPUTED_VALUE"""),"2024-06") -> 2024-06 | F2: =IFERROR(__xludf.DUMMYFUNCTION("""COMPUTED_VALUE"""),231.0) -> 231
A3: =IFERROR(__xludf.DUMMYFUNCTION("""COMPUTED_VALUE"""),"salario") -> salario | B3: =IFERROR(__xludf.DUMMYFUNCTION("""COMPUTED_VALUE"""),"Ingreso") -> Ingreso | C3: =IFERROR(__xludf.DUMMYFUNCTION("""COMPUTED_VALUE"""),"user-b") -> user-b | D3: =IFERROR(__xludf.DUMMYFUNCTION("""COMPUTED_VALUE"""),"Si") -> Si | E3: =IFERROR(__xludf.DUMMYFUNCTION("""COMPUTED_VALUE"""),"2024-06") -> 2024-06 | F3: =IFERROR(__xludf.DUMMYFUNCTION("""COMPUTED_VALUE"""),5175.0) -> 5175
A4: =IFERROR(__xludf.DUMMYFUNCTION("""COMPUTED_VALUE"""),"super") -> super | B4: =IFERROR(__xludf.DUMMYFUNCTION("""COMPUTED_VALUE"""),"Gasto") -> Gasto | C4: =IFERROR(__xludf.DUMMYFUNCTION("""COMPUTED_VALUE"""),"user-b") -> user-b | D4: =IFERROR(__xludf.DUMMYFUNCTION("""COMPUTED_VALUE"""),"Si") -> Si | E4: =IFERROR(__xludf.DUMMYFUNCTION("""COMPUTED_VALUE"""),"2024-06") -> 2024-06 | F4: =IFERROR(__xludf.DUMMYFUNCTION("""COMPUTED_VALUE"""),117.51824817518248) -> 117.51825
A5: =IFERROR(__xludf.DUMMYFUNCTION("""COMPUTED_VALUE"""),"salidas") -> salidas | B5: =IFERROR(__xludf.DUMMYFUNCTION("""COMPUTED_VALUE"""),"Gasto") -> Gasto | C5: =IFERROR(__xludf.DUMMYFUNCTION("""COMPUTED_VALUE"""),"user-b") -> user-b | D5: =IFERROR(__xludf.DUMMYFUNCTION("""COMPUTED_VALUE"""),"Si") -> Si | E5: =IFERROR(__xludf.DUMMYFUNCTION("""COMPUTED_VALUE"""),"2024-06") -> 2024-06 | F5: =IFERROR(__xludf.DUMMYFUNCTION("""COMPUTED_VALUE"""),258.3941605839416) -> 258.39416
A6: =IFERROR(__xludf.DUMMYFUNCTION("""COMPUTED_VALUE"""),"delivery") -> delivery | B6: =IFERROR(__xludf.DUMMYFUNCTION("""COMPUTED_VALUE"""),"Gasto") -> Gasto | C6: =IFERROR(__xludf.DUMMYFUNCTION("""COMPUTED_VALUE"""),"user-b") -> user-b | D6: =IFERROR(__xludf.DUMMYFUNCTION("""COMPUTED_VALUE"""),"Si") -> Si | E6: =IFERROR(__xludf.DUMMYFUNCTION("""COMPUTED_VALUE"""),"2024-06") -> 2024-06 | F6: =IFERROR(__xludf.DUMMYFUNCTION("""COMPUTED_VALUE"""),125.91240875912409) -> 125.91241
A7: =IFERROR(__xludf.DUMMYFUNCTION("""COMPUTED_VALUE"""),"otros") -> otros | B7: =IFERROR(__xludf.DUMMYFUNCTION("""COMPUTED_VALUE"""),"Gasto") -> Gasto | C7: =IFERROR(__xludf.DUMMYFUNCTION("""COMPUTED_VALUE"""),"user-b") -> user-b | D7: =IFERROR(__xludf.DUMMYFUNCTION("""COMPUTED_VALUE"""),"No") -> No | E7: =IFERROR(__xludf.DUMMYFUNCTION("""COMPUTED_VALUE"""),"2024-06") -> 2024-06 | F7: =IFERROR(__xludf.DUMMYFUNCTION("""COMPUTED_VALUE"""),209.03284671532847) -> 209.03285
A8: =IFERROR(__xludf.DUMMYFUNCTION("""COMPUTED_VALUE"""),"auto") -> auto | B8: =IFERROR(__xludf.DUMMYFUNCTION("""COMPUTED_VALUE"""),"Gasto") -> Gasto | C8: =IFERROR(__xludf.DUMMYFUNCTION("""COMPUTED_VALUE"""),"user-b") -> user-b | D8: =IFERROR(__xludf.DUMMYFUNCTION("""COMPUTED_VALUE"""),"Si") -> Si | E8: =IFERROR(__xludf.DUMMYFUNCTION("""COMPUTED_VALUE"""),"2024-06") -> 2024-06 | F8: =IFERROR(__xludf.DUMMYFUNCTION("""COMPUTED_VALUE"""),46.715328467153284) -> 46.715328
A9: =IFERROR(__xludf.DUMMYFUNCTION("""COMPUTED_VALUE"""),"nafta") -> nafta | B9: =IFERROR(__xludf.DUMMYFUNCTION("""COMPUTED_VALUE"""),"Gasto") -> Gasto | C9: =IFERROR(__xludf.DUMMYFUNCTION("""COMPUTED_VALUE"""),"user-b") -> user-b | D9: =IFERROR(__xludf.DUMMYFUNCTION("""COMPUTED_VALUE"""),"Si") -> Si | E9: =IFERROR(__xludf.DUMMYFUNCTION("""COMPUTED_VALUE"""),"2024-06") -> 2024-06 | F9: =IFERROR(__xludf.DUMMYFUNCTION("""COMPUTED_VALUE"""),16.05839416058394) -> 16.058394
A10: =IFERROR(__xludf.DUMMYFUNCTION("""COMPUTED_VALUE"""),"otros") -> otros | B10: =IFERROR(__xludf.DUMMYFUNCTION("""COMPUTED_VALUE"""),"Gasto") -> Gasto | C10: =IFERROR(__xludf.DUMMYFUNCTION("""COMPUTED_VALUE"""),"user-b") -> user-b | D10: =IFERROR(__xludf.DUMMYFUNCTION("""COMPUTED_VALUE"""),"No") -> No | E10: =IFERROR(__xludf.DUMMYFUNCTION("""COMPUTED_VALUE"""),"2024-07") -> 2024-07 | F10: =IFERROR(__xludf.DUMMYFUNCTION("""COMPUTED_VALUE"""),80.94615384615383) -> 80.946154
A11: =IFERROR(__xludf.DUMMYFUNCTION("""COMPUTED_VALUE"""),"super") -> super | B11: =IFERROR(__xludf.DUMMYFUNCTION("""COMPUTED_VALUE"""),"Gasto") -> Gasto | C11: =IFERROR(__xludf.DUMMYFUNCTION("""COMPUTED_VALUE"""),"user-b") -> user-b | D11: =IFERROR(__xludf.DUMMYFUNCTION("""COMPUTED_VALUE"""),"Si") -> Si | E11: =IFERROR(__xludf.DUMMYFUNCTION("""COMPUTED_VALUE"""),"2024-07") -> 2024-07 | F11: =IFERROR(__xludf.DUMMYFUNCTION("""COMPUTED_VALUE"""),212.66153846153847) -> 212.66154
A12: =IFERROR(__xludf.DUMMYFUNCTION("""COMPUTED_VALUE"""),"servicios") -> servicios | B12: =IFERROR(__xludf.DUMMYFUNCTION("""COMPUTED_VALUE"""),"Gasto") -> Gasto | C12: =IFERROR(__xludf.DUMMYFUNCTION("""COMPUTED_VALUE"""),"user-b") -> user-b | D12: =IFERROR(__xludf.DUMMYFUNCTION("""COMPUTED_VALUE"""),"Si") -> Si | E12: =IFERROR(__xludf.DUMMYFUNCTION("""COMPUTED_VALUE"""),"2024-07") -> 2024-07 | F12: =IFERROR(__xludf.DUMMYFUNCTION("""COMPUTED_VALUE"""),244.0) -> 244
A13: =IFERROR(__xludf.DUMMYFUNCTION("""COMPUTED_VALUE"""),"salario") -> salario | B13: =IFERROR(__xludf.DUMMYFUNCTION("""COMPUTED_VALUE"""),"Ingreso") -> Ingreso | C13: =IFERROR(__xludf.DUMMYFUNCTION("""COMPUTED_VALUE"""),"user-b") -> user-b | D13: =IFERROR(__xludf.DUMMYFUNCTION("""COMPUTED_VALUE"""),"Si") -> Si | E13: =IFERROR(__xludf.DUMMYFUNCTION("""COMPUTED_VALUE"""),"2024-07") -> 2024-07 | F13: =IFERROR(__xludf.DUMMYFUNCTION("""COMPUTED_VALUE"""),3750.0) -> 3750
A14: =IFERROR(__xludf.DUMMYFUNCTION("""COMPUTED_VALUE"""),"salidas") -> salidas | B14: =IFERROR(__xludf.DUMMYFUNCTION("""COMPUTED_VALUE"""),"Gasto") -> Gasto | C14: =IFERROR(__xludf.DUMMYFUNCTION("""COMPUTED_VALUE"""),"user-b") -> user-b | D14: =IFERROR(__xludf.DUMMYFUNCTION("""COMPUTED_VALUE"""),"Si") -> Si | E14: =IFERROR(__xludf.DUMMYFUNCTION("""COMPUTED_VALUE"""),"2024-07") -> 2024-07 | F14: =IFERROR(__xludf.DUMMYFUNCTION("""COMPUTED_VALUE"""),185.19230769230768) -> 185.19231
A15: =IFERROR(__xludf.DUMMYFUNCTION("""COMPUTED_VALUE"""),"delivery") -> delivery | B15: =IFERROR(__xludf.DUMMYFUNCTION("""COMPUTED_VALUE"""),"Gasto") -> Gasto | C15: =IFERROR(__xludf.DUMMYFUNCTION("""COMPUTED_VALUE"""),"user-b") -> user-b | D15: =IFERROR(__xludf.DUMMYFUNCTION("""COMPUTED_VALUE"""),"Si") -> Si | E15: =IFERROR(__xludf.DUMMYFUNCTION("""COMPUTED_VALUE"""),"2024-07") -> 2024-07 | F15: =IFERROR(__xludf.DUMMYFUNCTION("""COMPUTED_VALUE"""),172.23076923076923) -> 172.23077
A16: =IFERROR(__xludf.DUMMYFUNCTION("""COMPUTED_VALUE"""),"nafta") -> nafta | B16: =IFERROR(__xludf.DUMMYFUNCTION("""COMPUTED_VALUE"""),"Gasto") -> Gasto | C16: =IFERROR(__xludf.DUMMYFUNCTION("""COMPUTED_VALUE"""),"user-b") -> user-b | D16: =IFERROR(__xludf.DUMMYFUNCTION("""COMPUTED_VALUE"""),"Si") -> Si | E16: =IFERROR(__xludf.DUMMYFUNCTION("""COMPUTED_VALUE"""),"2024-07") -> 2024-07 | F16: =IFERROR(__xludf.DUMMYFUNCTION("""COMPUTED_VALUE"""),17.115384615384617) -> 17.115385
A17: =IFERROR(__xludf.DUMMYFUNCTION("""COMPUTED_VALUE"""),"auto") -> auto | B17: =IFERROR(__xludf.DUMMYFUNCTION("""COMPUTED_VALUE"""),"Gasto") -> Gasto | C17: =IFERROR(__xludf.DUMMYFUNCTION("""COMPUTED_VALUE"""),"user-b") -> user-b | D17: =IFERROR(__xludf.DUMMYFUNCTION("""COMPUTED_VALUE"""),"Si") -> Si | E17: =IFERROR(__xludf.DUMMYFUNCTION("""COMPUTED_VALUE"""),"2024-07") -> 2024-07 | F17: =IFERROR(__xludf.DUMMYFUNCTION("""COMPUTED_VALUE"""),135.96153846153845) -> 135.96154
A18: =IFERROR(__xludf.DUMMYFUNCTION("""COMPUTED_VALUE"""),"otros") -> otros | B18: =IFERROR(__xludf.DUMMYFUNCTION("""COMPUTED_VALUE"""),"Gasto") -> Gasto | C18: =IFERROR(__xludf.DUMMYFUNCTION("""COMPUTED_VALUE"""),"user-b") -> user-b | D18: =IFERROR(__xludf.DUMMYFUNCTION("""COMPUTED_VALUE"""),"No") -> No | E18: =IFERROR(__xludf.DUMMYFUNCTION("""COMPUTED_VALUE"""),"2024-08") -> 2024-08 | F18: =IFERROR(__xludf.DUMMYFUNCTION("""COMPUTED_VALUE"""),66.34008097165992) -> 66.340081
A19: =IFERROR(__xludf.DUMMYFUNCTION("""COMPUTED_VALUE"""),"super") -> super | B19: =IFERROR(__xludf.DUMMYFUNCTION("""COMPUTED_VALUE"""),"Gasto") -> Gasto | C19: =IFERROR(__xludf.DUMMYFUNCTION("""COMPUTED_VALUE"""),"user-b") -> user-b | D19: =IFERROR(__xludf.DUMMYFUNCTION("""COMPUTED_VALUE"""),"Si") -> Si | E19: =IFERROR(__xludf.DUMMYFUNCTION("""COMPUTED_VALUE"""),"2024-08") -> 2024-08 | F19: =IFERROR(__xludf.DUMMYFUNCTION("""COMPUTED_VALUE"""),65.31174089068826) -> 65.311741
A20: =IFERROR(__xludf.DUMMYFUNCTION("""COMPUTED_VALUE"""),"salidas") -> salidas | B20: =IFERROR(__xludf.DUMMYFUNCTION("""COMPUTED_VALUE"""),"Gasto") -> Gasto | C20: =IFERROR(__xludf.DUMMYFUNCTION("""COMPUTED_VALUE"""),"user-b") -> user-b | D20: =IFERROR(__xludf.DUMMYFUNCTION("""COMPUTED_VALUE"""),"Si") -> Si | E20: =IFERROR(__xludf.DUMMYFUNCTION("""COMPUTED_VALUE"""),"2024-08") -> 2024-08 | F20: =IFERROR(__xludf.DUMMYFUNCTION("""COMPUTED_VALUE"""),54.04858299595141) -> 54.048583
A21: =IFERROR(__xludf.DUMMYFUNCTION("""COMPUTED_VALUE"""),"auto") -> auto | B21: =IFERROR(__xludf.DUMMYFUNCTION("""COMPUTED_VALUE"""),"Gasto") -> Gasto | C21: =IFERROR(__xludf.DUMMYFUNCTION("""COMPUTED_VALUE"""),"user-b") -> user-b | D21: =IFERROR(__xludf.DUMMYFUNCTION("""COMPUTED_VALUE"""),"Si") -> Si | E21: =IFERROR(__xludf.DUMMYFUNCTION("""COMPUTED_VALUE"""),"2024-08") -> 2024-08 | F21: =IFERROR(__xludf.DUMMYFUNCTION("""COMPUTED_VALUE"""),20.850202429149796) -> 20.850202
A22: =IFERROR(__xludf.DUMMYFUNCTION("""COMPUTED_VALUE"""),"otros") -> otros | B22: =IFERROR(__xludf.DUMMYFUNCTION("""COMPUTED_VALUE"""),"Gasto") -> Gasto | C22: =IFERROR(__xludf.DUMMYFUNCTION("""COMPUTED_VALUE"""),"user-b") -> user-b | D22: =IFERROR(__xludf.DUMMYFUNCTION("""COMPUTED_VALUE"""),"No") -> No | E22: =IFERROR(__xludf.DUMMYFUNCTION("""COMPUTED_VALUE"""),"2024-09") -> 2024-09 | F22: =IFERROR(__xludf.DUMMYFUNCTION("""COMPUTED_VALUE"""),45.123966942148755) -> 45.123967
A23: =IFERROR(__xludf.DUMMYFUNCTION("""COMPUTED_VALUE"""),"salidas") -> salidas | B23: =IFERROR(__xludf.DUMMYFUNCTION("""COMPUTED_VALUE"""),"Gasto") -> Gasto | C23: =IFERROR(__xludf.DUMMYFUNCTION("""COMPUTED_VALUE"""),"user-b") -> user-b | D23: =IFERROR(__xludf.DUMMYFUNCTION("""COMPUTED_VALUE"""),"Si") -> Si | E23: =IFERROR(__xludf.DUMMYFUNCTION("""COMPUTED_VALUE"""),"2024-09") -> 2024-09 | F23: =IFERROR(__xludf.DUMMYFUNCTION("""COMPUTED_VALUE"""),49.65289256198348) -> 49.652893
A24: =IFERROR(__xludf.DUMMYFUNCTION("""COMPUTED_VALUE"""),"super") -> super | B24: =IFERROR(__xludf.DUMMYFUNCTION("""COMPUTED_VALUE"""),"Gasto") -> Gasto | C24: =IFERROR(__xludf.DUMMYFUNCTION("""COMPUTED_VALUE"""),"user-b") -> user-b | D24: =IFERROR(__xludf.DUMMYFUNCTION("""COMPUTED_VALUE"""),"Si") -> Si | E24: =IFERROR(__xludf.DUMMYFUNCTION("""COMPUTED_VALUE"""),"2024-09") -> 2024-09 | F24: =IFERROR(__xludf.DUMMYFUNCTION("""COMPUTED_VALUE"""),45.17355371900827) -> 45.173554
A25: =IFERROR(__xludf.DUMMYFUNCTION("""COMPUTED_VALUE"""),"auto") -> auto | B25: =IFERROR(__xludf.DUMMYFUNCTION("""COMPUTED_VALUE"""),"Gasto") -> Gasto | C25: =IFERROR(__xludf.DUMMYFUNCTION("""COMPUTED_VALUE"""),"user-b") -> user-b | D25: =IFERROR(__xludf.DUMMYFUNCTION("""COMPUTED_VALUE"""),"Si") -> Si | E25: =IFERROR(__xludf.DUMMYFUNCTION("""COMPUTED_VALUE"""),"2024-09") -> 2024-09 | F25: =IFERROR(__xludf.DUMMYFUNCTION("""COMPUTED_VALUE"""),21.28099173553719) -> 21.280992
A26: =IFERROR(__xludf.DUMMYFUNCTION("""COMPUTED_VALUE"""),"otros") -> otros | B26: =IFERROR(__xludf.DUMMYFUNCTION("""COMPUTED_VALUE"""),"Gasto") -> Gasto | C26: =IFERROR(__xludf.DUMMYFUNCTION("""COMPUTED_VALUE"""),"user-b") -> user-b | D26: =IFERROR(__xludf.DUMMYFUNCTION("""COMPUTED_VALUE"""),"No") -> No | E26: =IFERROR(__xludf.DUMMYFUNCTION("""COMPUTED_VALUE"""),"2024-10") -> 2024-10 | F26: =IFERROR(__xludf.DUMMYFUNCTION("""COMPUTED_VALUE"""),47.89473684210526) -> 47.894737
A27: =IFERROR(__xludf.DUMMYFUNCTION("""COMPUTED_VALUE"""),"auto") -> auto | B27: =IFERROR(__xludf.DUMMYFUNCTION("""COMPUTED_VALUE"""),"Gasto") -> Gasto | C27: =IFERROR(__xludf.DUMMYFUNCTION("""COMPUTED_VALUE"""),"user-b") -> user-b | D27: =IFERROR(__xludf.DUMMYFUNCTION("""COMPUTED_VALUE"""),"Si") -> Si | E27: =IFERROR(__xludf.DUMMYFUNCTION("""COMPUTED_VALUE"""),"2024-10") -> 2024-10 | F27: =IFERROR(__xludf.DUMMYFUNCTION("""COMPUTED_VALUE"""),22.587719298245613) -> 22.587719
A28: =IFERROR(__xludf.DUMMYFUNCTION("""COMPUTED_VALUE"""),"salidas") -> salidas | B28: =IFERROR(__xludf.DUMMYFUNCTION("""COMPUTED_VALUE"""),"Gasto") -> Gasto | C28: =IFERROR(__xludf.DUMMYFUNCTION("""COMPUTED_VALUE"""),"user-b") -> user-b | D28: =IFERROR(__xludf.DUMMYFUNCTION("""COMPUTED_VALUE"""),"Si") -> Si | E28: =IFERROR(__xludf.DUMMYFUNCTION("""COMPUTED_VALUE"""),"2024-10") -> 2024-10 | F28: =IFERROR(__xludf.DUMMYFUNCTION("""COMPUTED_VALUE"""),5.850877192982456) -> 5.8508772
A29: =IFERROR(__xludf.DUMMYFUNCTION("""COMPUTED_VALUE"""),"otros") -> otros | B29: =IFERROR(__xludf.DUMMYFUNCTION("""COMPUTED_VALUE"""),"Gasto") -> Gasto | C29: =IFERROR(__xludf.DUMMYFUNCTION("""COMPUTED_VALUE"""),"user-b") -> user-b | D29: =IFERROR(__xludf.DUMMYFUNCTION("""COMPUTED_VALUE"""),"No") -> No | E29: =IFERROR(__xludf.DUMMYFUNCTION("""COMPUTED_VALUE"""),"2024-11") -> 2024-11 | F29: =IFERROR(__xludf.DUMMYFUNCTION("""COMPUTED_VALUE"""),50.79069767441861) -> 50.790698
A30: =IFERROR(__xludf.DUMMYFUNCTION("""COMPUTED_VALUE"""),"auto") -> auto | B30: =IFERROR(__xludf.DUMMYFUNCTION("""COMPUTED_VALUE"""),"Gasto") -> Gasto | C30: =IFERROR(__xludf.DUMMYFUNCTION("""COMPUTED_VALUE"""),"user-b") -> user-b | D30: =IFERROR(__xludf.DUMMYFUNCTION("""COMPUTED_VALUE"""),"Si") -> Si | E30: =IFERROR(__xludf.DUMMYFUNCTION("""COMPUTED_VALUE"""),"2024-11") -> 2024-11 | F30: =IFERROR(__xludf.DUMMYFUNCTION("""COMPUTED_VALUE"""),23.953488372093023) -> 23.953488
A31: =IFERROR(__xludf.DUMMYFUNCTION("""COMPUTED_VALUE"""),"otros") -> otros | B31: =IFERROR(__xludf.DUMMYFUNCTION("""COMPUTED_VALUE"""),"Gasto") -> Gasto | C31: =IFERROR(__xludf.DUMMYFUNCTION("""COMPUTED_VALUE"""),"user-b") -> user-b | D31: =IFERROR(__xludf.DUMMYFUNCTION("""COMPUTED_VALUE"""),"No") -> No | E31: =IFERROR(__xludf.DUMMYFUNCTION("""COMPUTED_VALUE"""),"2024-12") -> 2024-12 | F31: =IFERROR(__xludf.DUMMYFUNCTION("""COMPUTED_VALUE"""),32.98695652173914) -> 32.986957
A32: =IFERROR(__xludf.DUMMYFUNCTION("""COMPUTED_VALUE"""),"auto") -> auto | B32: =IFERROR(__xludf.DUMMYFUNCTION("""COMPUTED_VALUE"""),"Gasto") -> Gasto | C32: =IFERROR(__xludf.DUMMYFUNCTION("""COMPUTED_VALUE"""),"user-b") -> user-b | D32: =IFERROR(__xludf.DUMMYFUNCTION("""COMPUTED_VALUE"""),"Si") -> Si | E32: =IFERROR(__xludf.DUMMYFUNCTION("""COMPUTED_VALUE"""),"2024-12") -> 2024-12 | F32: =IFERROR(__xludf.DUMMYFUNCTION("""COMPUTED_VALUE"""),22.391304347826086) -> 22.391304

Sheet expenses
A1: Id | B1: Período | C1: Categoría | D1: Monto | E1: Cuotas | F1: Moneda | G1: Comentario | H1: Ingreso/Egreso | I1: Compartido | J1: usuario
A2: c88c1ddc-0a86-11f1-af1e-325096b39f47 | B2: 45444 | C2: servicios | D2: 231 | E2: 1 | F2: USD | H2: Egreso | I2: Si | J2: user-b
A3: 00349dd4-0ab1-11f1-81b6-325096b39f47 | B3: 45444 | C3: salario | D3: 1500 | E3: 1 | F3: USD | H3: Ingreso | I3: Si | J3: user-b
A4: 5c80570a | B4: 45451 | C4: super | D4: 6000 | E4: 1 | F4: ARS | H4: Egreso | I4: Si | J4: user-b
A5: e29fba8f | B5: 45451 | C5: salidas | D5: 42000 | E5: 1 | F5: ARS | H5: Egreso | I5: Si | J5: user-b
A6: ba548b7a | B6: 45452 | C6: super | D6: 62000 | E6: 1 | F6: ARS | H6: Egreso | I6: Si | J6: user-b
A7: 84763a1b | B7: 45452 | C7: delivery | D7: 14000 | E7: 1 | F7: ARS | H7: Egreso | I7: Si | J7: user-b
A8: 598b7297 | B8: 45453 | C8: delivery | D8: 9500 | E8: 1 | F8: ARS | H8: Egreso | I8: Si | J8: user-b
A9: 2ca822bc | B9: 45454 | C9: delivery | D9: 12000 | E9: 1 | F9: ARS | H9: Egreso | I9: Si | J9: user-b
A10: 1550232e | B10: 45454 | C10: salidas | D10: 36000 | E10: 1 | F10: ARS | H10: Egreso | I10: Si | J10: user-b
A11: c17d2e81 | B11: 45455 | C11: super | D11: 2000 | E11: 1 | F11: ARS | H11: Egreso | I11: Si | J11: user-b
A12: 0064096d | B12: 45456 | C12: otros | D12: 45990 | E12: 3 | F12: ARS | G12: Teclado | H12: Egreso | I12: No | J12: user-b
A13: 3d675d52 | B13: 45456 | C13: delivery | D13: 10000 | E13: 1 | F13: ARS | H13: Egreso | I13: Si | J13: user-b
A14: 2242ddfb | B14: 45457 | C14: delivery | D14: 26000 | E14: 1 | F14: ARS | H14: Egreso | I14: Si | J14: user-b
A15: d59172c2 | B15: 45458 | C15: delivery | D15: 36000 | E15: 1 | F15: ARS | H15: Egreso | I15: Si | J15: user-b
A16: c21ccf8d | B16: 45458 | C16: super | D16: 8000 | E16: 1 | F16: ARS | H16: Egreso | I16: Si | J16: user-b
A17: f7a63002 | B17: 45458 | C17: otros | D17: 4000 | E17: 1 | F17: ARS | H17: Egreso | I17: No | J17: user-b
A18: 625bdd9f | B18: 45459 | C18: otros | D18: 13 | E18: 1 | F18: USD | G18: Android games | H18: Egreso | I18: No | J18: user-b
A19: 018508b9 | B19: 45459 | C19: salidas | D19: 19000 | E19: 1 | F19: ARS | G19: Cine | H19: Egreso | I19: Si | J19: user-b
A20: 0678954a | B20: 45459 | C20: super | D20: 12000 | E20: 3 | F20: ARS | H20: Egreso | I20: Si | J20: user-b
A21: 401cbf11 | B21: 45460 | C21: super | D21: 15990 | E21: 3 | F21: ARS | G21: Café | H21: Egreso | I21: Si | J21: user-b
A22: 940e81b5 | B22: 45460 | C22: delivery | D22: 22000 | E22: 1 | F22: ARS | H22: Egreso | I22: Si | J22: user-b
A23: d4ef954e | B23: 45460 | C23: super | D23: 15000 | E23: 1 | F23: ARS | H23: Egreso | I23: Si | J23: user-b
A24: fdc86f90 | B24: 45461 | C24: delivery | D24: 10000 | E24: 1 | F24: ARS | H24: Egreso | I24: Si | J24: user-b
A25: a3ee2198 | B25: 45462 | C25: super | D25: 32010 | E25: 3 | F25: ARS | H25: Egreso | I25: Si | J25: user-b
A26: 708768c6 | B26: 45463 | C26: super | D26: 18000 | E26: 3 | F26: ARS | G26: Farmacia | H26: Egreso | I26: Si | J26: user-b
A27: 598090be | B27: 45463 | C27: otros | D27: 99990 | E27: 6 | F27: ARS | G27: Ropa y regalo | H27: Egreso | I27: No | J27: user-b
A28: 0fb61cb0 | B28: 45463 | C28: super | D28: 32000 | E28: 1 | F28: ARS | H28: Egreso | I28: Si | J28: user-b
A29: 03ed6348 | B29: 45464 | C29: auto | D29: 64000 | E29: 1 | F29: ARS | G29: Seguro | H29: Egreso | I29: Si | J29: user-b
A30: 9512b155 | B30: 45464 | C30: salidas | D30: 46000 | E30: 1 | F30: ARS | H30: Egreso | I30: Si | J30: user-b
A31: 9d6c1d28 | B31: 45465 | C31: otros | D31: 150 | E31: 1 | F31: USD | G31: joysticks | H31: Egreso | I31: No | J31: user-b
A32: 46d5ddb2 | B32: 45465 | C32: otros | D32: 11 | E32: 1 | F32: USD | G32: Steam | H32: Egreso | I32: No | J32: user-b
A33: a75d03e8 | B33: 45465 | C33: delivery | D33: 11000 | E33: 1 | F33: ARS | H33: Egreso | I33: Si | J33: user-b
A34: 5dc0634c | B34: 45467 | C34: nafta | D34: 22000 | E34: 1 | F34: ARS | H34: Egreso | I34: Si | J34: user-b
A35: 55adfa1b | B35: 45468 | C35: otros | D35: 36000 | E35: 3 | F35: ARS | G35: micro sd | H35: Egreso | I35: No | J35: user-b
A36: 1c07f07c | B36: 45469 | C36: delivery | D36: 8000 | E36: 1 | F36: ARS | H36: Egreso | I36: Si | J36: user-b
A37: f4f9ecd1 | B37: 45470 | C37: salidas | D37: 70000 | E37: 1 | F37: ARS | H37: Egreso | I37: Si | J37: user-b
A38: ca631e01 | B38: 45471 | C38: delivery | D38: 14000 | E38: 1 | F38: ARS | H38: Egreso | I38: Si | J38: user-b
A39: 7c6577c4 | B39: 45472 | C39: salidas | D39: 45000 | E39: 1 | F39: ARS | G39: Almuerzo floa | H39: Egreso | I39: Si | J39: user-b
A40: 3308ceed | B40: 45472 | C40: salidas | D40: 40000 | E40: 1 | F40: ARS | H40: Egreso | I40: Si | J40: user-b
A41: ea3dfdfd | B41: 45472 | C41: super | D41: 10000 | E41: 1 | F41: ARS | H41: Egreso | I41: Si | J41: user-b
A42: bc488748 | B42: 45472 | C42: salidas | D42: 56000 | E42: 1 | F42: ARS | H42: Egreso | I42: Si | J42: user-b
A43: e08fd082 | B43: 45474 | C43: super | D43: 1200 | E43: 1 | F43: ARS | H43: Egreso | I43: Si | J43: user-b
A44: c88c2016-0a86-11f1-b3ca-325096b39f47 | B44: 45474 | C44: servicios | D44: 244 | E44: 1 | F44: USD | H44: Egreso | I44: Si | J44: user-b
A45: 0034a018-0ab1-11f1-9ac3-325096b39f47 | B45: 45474 | C45: salario | D45: 1500 | E45: 1 | F45: USD | H45: Ingreso | I45: Si | J45: user-b
A46: 0bad2316 | B46: 45475 | C46: salidas | D46: 73000 | E46: 1 | F46: ARS | G46: Nanum | H46: Egreso | I46: Si | J46: user-b
A47: 8fae5122 | B47: 45475 | C47: delivery | D47: 5000 | E47: 1 | F47: ARS | H47: Egreso | I47: Si | J47: user-b
A48: b269c650 | B48: 45475 | C48: super | D48: 20000 | E48: 1 | F48: ARS | H48: Egreso | I48: Si | J48: user-b
A49: 7b3d6c53 | B49: 45476 | C49: otros | D49: 11490 | E49: 6 | F49: ARS | G49: Cargador celu | H49: Egreso | I49: No | J49: user-b
A50: 2094c0cd | B50: 45477 | C50: delivery | D50: 17000 | E50: 1 | F50: ARS | H50: Egreso | I50: Si | J50: user-b
A51: 193f55c0 | B51: 45478 | C51: super | D51: 27000 | E51: 1 | F51: ARS | H51: Egreso | I51: Si | J51: user-b
A52: a429de0f | B52: 45479 | C52: delivery | D52: 9300 | E52: 1 | F52: ARS | H52: Egreso | I52: Si | J52: user-b
A53: 29b8c40a | B53: 45479 | C53: salidas | D53: 15000 | E53: 3 | F53: ARS | H53: Egreso | I53: Si | J53: user-b
A54: 97d9c6f9 | B54: 45479 | C54: super | D54: 6000 | E54: 3 | F54: ARS | H54: Egreso | I54: Si | J54: user-b
A55: 35a42b0b | B55: 45480 | C55: otros | D55: 1 | E55: 1 | F55: USD | G55: Android | H55: Egreso | I55: No | J55: user-b
A56: a855b173 | B56: 45480 | C56: salidas | D56: 23000 | E56: 1 | F56: ARS | H56: Egreso | I56: Si | J56: user-b
A57: cbcc13f9 | B57: 45482 | C57: salidas | D57: 32000 | E57: 1 | F57: ARS | H57: Egreso | I57: Si | J57: user-b
A58: ffcdd5ac | B58: 45482 | C58: delivery | D58: 15000 | E58: 1 | F58: ARS | H58: Egreso | I58: Si | J58: user-b
A59: 7040a3b2 | B59: 45482 | C59: super | D59: 114000 | E59: 3 | F59: ARS | H59: Egreso | I59: Si | J59: user-b
A60: 20d9aee0 | B60: 45483 | C60: delivery | D60: 25500 | E60: 1 | F60: ARS | H60: Egreso | I60: Si | J60: user-b
A61: 28e367aa | B61: 45483 | C61: otros | D61: 11610 | E61: 6 | F61: ARS | H61: Egreso | I61: No | J61: user-b
A62: 15a4d87d | B62: 45485 | C62: delivery | D62: 11000 | E62: 1 | F62: ARS | H62: Egreso | I62: Si | J62: user-b
A63: 0c9a78ab | B63: 45486 | C63: otros | D63: 13000 | E63: 1 | F63: ARS | G63: Clases | H63: Egreso | I63: No | J63: user-b
A64: 6dc272f0 | B64: 45486 | C64: super | D64: 12000 | E64: 1 | F64: ARS | H64: Egreso | I64: Si | J64: user-b
A65: 8faed62b | B65: 45486 | C65: delivery | D65: 9000 | E65: 1 | F65: ARS | H65: Egreso | I65: Si | J65: user-b
A66: a6cdee20 | B66: 45486 | C66: delivery | D66: 3000 | E66: 1 | F66: ARS | H66: Egreso | I66: Si | J66: user-b
A67: 886144ce | B67: 45486 | C67: super | D67: 18000 | E67: 1 | F67: ARS | H67: Egreso | I67: Si | J67: user-b
A68: 5ca39062 | B68: 45487 | C68: super | D68: 9990 | E68: 3 | F68: ARS | H68: Egreso | I68: Si | J68: user-b
A69: 81d03a25 | B69: 45487 | C69: salidas | D69: 23610 | E69: 3 | F69: ARS | H69: Egreso | I69: Si | J69: user-b
A70: 2573dcf3 | B70: 45488 | C70: otros | D70: 35010 | E70: 6 | F70: ARS | G70: Google home | H70: Egreso | I70: No | J70: user-b
A71: addd52da | B71: 45488 | C71: super | D71: 7000 | E71: 1 | F71: ARS | H71: Egreso | I71: Si | J71: user-b
A72: d51c753f | B72: 45488 | C72: nafta | D72: 22250 | E72: 1 | F72: ARS | H72: Egreso | I72: Si | J72: user-b
A73: 35e82ccf | B73: 45489 | C73: auto | D73: 87000 | E73: 1 | F73: ARS | G73: Patente | H73: Egreso | I73: Si | J73: user-b
A74: d3a7affb | B74: 45490 | C74: super | D74: 21000 | E74: 3 | F74: ARS | G74: Cafe | H74: Egreso | I74: Si | J74: user-b
A75: ec9ad7b2 | B75: 45490 | C75: otros | D75: 85500 | E75: 6 | F75: ARS | G75: Estufa | H75: Egreso | I75: No | J75: user-b
A76: 150b4df9 | B76: 45490 | C76: delivery | D76: 12000 | E76: 1 | F76: ARS | H76: Egreso | I76: Si | J76: user-b
A77: b1a0fb8f | B77: 45491 | C77: delivery | D77: 4000 | E77: 1 | F77: ARS | H77: Egreso | I77: Si | J77: user-b
A78: a1ab32e2 | B78: 45491 | C78: salidas | D78: 98310 | E78: 3 | F78: ARS | H78: Egreso | I78: Si | J78: user-b
A79: 7634397d | B79: 45492 | C79: super | D79: 50000 | E79: 1 | F79: ARS | H79: Egreso | I79: Si | J79: user-b
A80: 8b77c84e | B80: 45493 | C80: otros | D80: 48990 | E80: 6 | F80: ARS | G80: Samsung fit3 | H80: Egreso | I80: No | J80: user-b
A81: b85d2bd0 | B81: 45493 | C81: super | D81: 14000 | E81: 1 | F81: ARS | H81: Egreso | I81: Si | J81: user-b
A82: 03ed6349 | B82: 45494 | C82: auto | D82: 64000 | E82: 1 | F82: ARS | G82: Seguro | H82: Egreso | I82: Si | J82: user-b
A83: 25c12033 | B83: 45494 | C83: delivery | D83: 17000 | E83: 1 | F83: ARS | H83: Egreso | I83: Si | J83: user-b
A84: 446d4157 | B84: 45495 | C84: super | D84: 4000 | E84: 1 | F84: ARS | H84: Egreso | I84: Si | J84: user-b
A85: d4cfdf71 | B85: 45495 | C85: delivery | D85: 26000 | E85: 1 | F85: ARS | H85: Egreso | I85: Si | J85: user-b
A86: 4ab582e0 | B86: 45496 | C86: delivery | D86: 12000 | E86: 1 | F86: ARS | H86: Egreso | I86: Si | J86: user-b
A87: 821811f1 | B87: 45497 | C87: delivery | D87: 8100 | E87: 1 | F87: ARS | H87: Egreso | I87: Si | J87: user-b
A88: 69f7905b | B88: 45498 | C88: delivery | D88: 4000 | E88: 1 | F88: ARS | H88: Egreso | I88: Si | J88: user-b
A89: d7741124 | B89: 45498 | C89: super | D89: 12990 | E89: 3 | F89: ARS | H89: Egreso | I89: Si | J89: user-b
A90: da5abf26 | B90: 45499 | C90: super | D90: 15000 | E90: 1 | F90: ARS | H90: Egreso | I90: Si | J90: user-b
A91: 57a3a46c | B91: 45500 | C91: otros | D91: 35010 | E91: 6 | F91: ARS | G91: Anker | H91: Egreso | I91: No | J91: user-b
A92: 1e479b68 | B92: 45500 | C92: super | D92: 15000 | E92: 1 | F92: ARS | H92: Egreso | I92: Si | J92: user-b
A93: 67937924 | B93: 45500 | C93: delivery | D93: 36000 | E93: 1 | F93: ARS | H93: Egreso | I93: Si | J93: user-b
A94: 2592f00c | B94: 45500 | C94: salidas | D94: 26010 | E94: 3 | F94: ARS | H94: Egreso | I94: Si | J94: user-b
A95: dfba7d23 | B95: 45501 | C95: auto | D95: 12000 | E95: 6 | F95: ARS | G95: Productos limpieza | H95: Egreso | I95: Si | J95: user-b
A96: 9a863c47 | B96: 45501 | C96: salidas | D96: 17310 | E96: 3 | F96: ARS | H96: Egreso | I96: Si | J96: user-b
A97: 268d617c | B97: 45502 | C97: otros | D97: 9000 | E97: 1 | F97: ARS | H97: Egreso | I97: No | J97: user-b
A98: 56b7d638 | B98: 45502 | C98: salidas | D98: 46000 | E98: 1 | F98: ARS | H98: Egreso | I98: Si | J98: user-b
A99: 5a95775b | B99: 45502 | C99: super | D99: 4000 | E99: 1 | F99: ARS | H99: Egreso | I99: Si | J99: user-b
A100: 45731286 | B100: 45503 | C100: auto | D100: 142500 | E100: 6 | F100: ARS | G100: Service | H100: Egreso | I100: Si | J100: user-b
...

Sheet expenses_by_installments
A1: ID | B1: PERÍODO | C1: PERIODO_ORIGEN | D1: CATEGORÍA | E1: MONTO CUOTA | F1: CUOTAS | G1: MONEDA | H1: COMENTARIO | I1: INGRESO/EGRESO | J1: COMPARTIDO | K1: USUARIO | L1: USD (MES CUOTA) | M1: USD (ORIGEN) | N1: MES-AÑO
A2: c88c1ddc-0a86-11f1-af1e-325096b39f47 | B2: 45444 | C2: 45444 | D2: servicios | E2: 231 | F2: 1 | G2: USD | I2: Egreso | J2: Si | K2: user-b | L2: 231 | M2: 231 | N2: 06-2024
A3: 00349dd4-0ab1-11f1-81b6-325096b39f47 | B3: 45444 | C3: 45444 | D3: salario | E3: 1500 | F3: 1 | G3: USD | I3: Ingreso | J3: Si | K3: user-b | L3: 5175 | M3: 5175 | N3: 06-2024
A4: 5c80570a | B4: 45451 | C4: 45451 | D4: super | E4: 6000 | F4: 1 | G4: ARS | I4: Egreso | J4: Si | K4: user-b | L4: 4.379562 | M4: 4.379562 | N4: 06-2024
A5: e29fba8f | B5: 45451 | C5: 45451 | D5: salidas | E5: 42000 | F5: 1 | G5: ARS | I5: Egreso | J5: Si | K5: user-b | L5: 30.656934 | M5: 30.656934 | N5: 06-2024
A6: ba548b7a | B6: 45452 | C6: 45452 | D6: super | E6: 62000 | F6: 1 | G6: ARS | I6: Egreso | J6: Si | K6: user-b | L6: 45.255474 | M6: 45.255474 | N6: 06-2024
A7: 84763a1b | B7: 45452 | C7: 45452 | D7: delivery | E7: 14000 | F7: 1 | G7: ARS | I7: Egreso | J7: Si | K7: user-b | L7: 10.218978 | M7: 10.218978 | N7: 06-2024
A8: 598b7297 | B8: 45453 | C8: 45453 | D8: delivery | E8: 9500 | F8: 1 | G8: ARS | I8: Egreso | J8: Si | K8: user-b | L8: 6.9343066 | M8: 6.9343066 | N8: 06-2024
A9: 2ca822bc | B9: 45454 | C9: 45454 | D9: delivery | E9: 12000 | F9: 1 | G9: ARS | I9: Egreso | J9: Si | K9: user-b | L9: 8.7591241 | M9: 8.7591241 | N9: 06-2024
A10: 1550232e | B10: 45454 | C10: 45454 | D10: salidas | E10: 36000 | F10: 1 | G10: ARS | I10: Egreso | J10: Si | K10: user-b | L10: 26.277372 | M10: 26.277372 | N10: 06-2024
A11: c17d2e81 | B11: 45455 | C11: 45455 | D11: super | E11: 2000 | F11: 1 | G11: ARS | I11: Egreso | J11: Si | K11: user-b | L11: 1.459854 | M11: 1.459854 | N11: 06-2024
A12: 0064096d | B12: 45456 | C12: 45456 | D12: otros | E12: 15330 | F12: 3 | G12: ARS | H12: Teclado | I12: Egreso | J12: No | K12: user-b | L12: 11.189781 | M12: 11.189781 | N12: 06-2024
A13: 0064096d | B13: 45486 | C13: 45456 | D13: otros | E13: 15330 | F13: 3 | G13: ARS | H13: Teclado | I13: Egreso | J13: No | K13: user-b | L13: 11.792308 | M13: 11.189781 | N13: 07-2024
A14: 0064096d | B14: 45517 | C14: 45456 | D14: otros | E14: 15330 | F14: 3 | G14: ARS | H14: Teclado | I14: Egreso | J14: No | K14: user-b | L14: 12.412955 | M14: 11.189781 | N14: 08-2024
A15: 3d675d52 | B15: 45456 | C15: 45456 | D15: delivery | E15: 10000 | F15: 1 | G15: ARS | I15: Egreso | J15: Si | K15: user-b | L15: 7.2992701 | M15: 7.2992701 | N15: 06-2024
A16: 2242ddfb | B16: 45457 | C16: 45457 | D16: delivery | E16: 26000 | F16: 1 | G16: ARS | I16: Egreso | J16: Si | K16: user-b | L16: 18.978102 | M16: 18.978102 | N16: 06-2024
A17: d59172c2 | B17: 45458 | C17: 45458 | D17: delivery | E17: 36000 | F17: 1 | G17: ARS | I17: Egreso | J17: Si | K17: user-b | L17: 26.277372 | M17: 26.277372 | N17: 06-2024
A18: c21ccf8d | B18: 45458 | C18: 45458 | D18: super | E18: 8000 | F18: 1 | G18: ARS | I18: Egreso | J18: Si | K18: user-b | L18: 5.8394161 | M18: 5.8394161 | N18: 06-2024
A19: f7a63002 | B19: 45458 | C19: 45458 | D19: otros | E19: 4000 | F19: 1 | G19: ARS | I19: Egreso | J19: No | K19: user-b | L19: 2.919708 | M19: 2.919708 | N19: 06-2024
A20: 625bdd9f | B20: 45459 | C20: 45459 | D20: otros | E20: 13 | F20: 1 | G20: USD | H20: Android games | I20: Egreso | J20: No | K20: user-b | L20: 13 | M20: 13 | N20: 06-2024
A21: 018508b9 | B21: 45459 | C21: 45459 | D21: salidas | E21: 19000 | F21: 1 | G21: ARS | H21: Cine | I21: Egreso | J21: Si | K21: user-b | L21: 13.868613 | M21: 13.868613 | N21: 06-2024
A22: 0678954a | B22: 45459 | C22: 45459 | D22: super | E22: 4000 | F22: 3 | G22: ARS | I22: Egreso | J22: Si | K22: user-b | L22: 2.919708 | M22: 2.919708 | N22: 06-2024
A23: 0678954a | B23: 45489 | C23: 45459 | D23: super | E23: 4000 | F23: 3 | G23: ARS | I23: Egreso | J23: Si | K23: user-b | L23: 3.0769231 | M23: 2.919708 | N23: 07-2024
A24: 0678954a | B24: 45520 | C24: 45459 | D24: super | E24: 4000 | F24: 3 | G24: ARS | I24: Egreso | J24: Si | K24: user-b | L24: 3.2388664 | M24: 2.919708 | N24: 08-2024
A25: 401cbf11 | B25: 45460 | C25: 45460 | D25: super | E25: 5330 | F25: 3 | G25: ARS | H25: Café | I25: Egreso | J25: Si | K25: user-b | L25: 3.8905109 | M25: 3.8905109 | N25: 06-2024
A26: 401cbf11 | B26: 45490 | C26: 45460 | D26: super | E26: 5330 | F26: 3 | G26: ARS | H26: Café | I26: Egreso | J26: Si | K26: user-b | L26: 4.1 | M26: 3.8905109 | N26: 07-2024
A27: 401cbf11 | B27: 45521 | C27: 45460 | D27: super | E27: 5330 | F27: 3 | G27: ARS | H27: Café | I27: Egreso | J27: Si | K27: user-b | L27: 4.3157895 | M27: 3.8905109 | N27: 08-2024
A28: 940e81b5 | B28: 45460 | C28: 45460 | D28: delivery | E28: 22000 | F28: 1 | G28: ARS | I28: Egreso | J28: Si | K28: user-b | L28: 16.058394 | M28: 16.058394 | N28: 06-2024
A29: d4ef954e | B29: 45460 | C29: 45460 | D29: super | E29: 15000 | F29: 1 | G29: ARS | I29: Egreso | J29: Si | K29: user-b | L29: 10.948905 | M29: 10.948905 | N29: 06-2024
A30: fdc86f90 | B30: 45461 | C30: 45461 | D30: delivery | E30: 10000 | F30: 1 | G30: ARS | I30: Egreso | J30: Si | K30: user-b | L30: 7.2992701 | M30: 7.2992701 | N30: 06-2024
A31: a3ee2198 | B31: 45462 | C31: 45462 | D31: super | E31: 10670 | F31: 3 | G31: ARS | I31: Egreso | J31: Si | K31: user-b | L31: 7.7883212 | M31: 7.7883212 | N31: 06-2024
A32: a3ee2198 | B32: 45492 | C32: 45462 | D32: super | E32: 10670 | F32: 3 | G32: ARS | I32: Egreso | J32: Si | K32: user-b | L32: 8.2076923 | M32: 7.7883212 | N32: 07-2024
A33: a3ee2198 | B33: 45523 | C33: 45462 | D33: super | E33: 10670 | F33: 3 | G33: ARS | I33: Egreso | J33: Si | K33: user-b | L33: 8.6396761 | M33: 7.7883212 | N33: 08-2024
A34: 708768c6 | B34: 45463 | C34: 45463 | D34: super | E34: 6000 | F34: 3 | G34: ARS | H34: Farmacia | I34: Egreso | J34: Si | K34: user-b | L34: 4.379562 | M34: 4.379562 | N34: 06-2024
A35: 708768c6 | B35: 45493 | C35: 45463 | D35: super | E35: 6000 | F35: 3 | G35: ARS | H35: Farmacia | I35: Egreso | J35: Si | K35: user-b | L35: 4.6153846 | M35: 4.379562 | N35: 07-2024
A36: 708768c6 | B36: 45524 | C36: 45463 | D36: super | E36: 6000 | F36: 3 | G36: ARS | H36: Farmacia | I36: Egreso | J36: Si | K36: user-b | L36: 4.8582996 | M36: 4.379562 | N36: 08-2024
A37: 598090be | B37: 45463 | C37: 45463 | D37: otros | E37: 16665 | F37: 6 | G37: ARS | H37: Ropa y regalo | I37: Egreso | J37: No | K37: user-b | L37: 12.164234 | M37: 12.164234 | N37: 06-2024
A38: 598090be | B38: 45493 | C38: 45463 | D38: otros | E38: 16665 | F38: 6 | G38: ARS | H38: Ropa y regalo | I38: Egreso | J38: No | K38: user-b | L38: 12.819231 | M38: 12.164234 | N38: 07-2024
A39: 598090be | B39: 45524 | C39: 45463 | D39: otros | E39: 16665 | F39: 6 | G39: ARS | H39: Ropa y regalo | I39: Egreso | J39: No | K39: user-b | L39: 13.493927 | M39: 12.164234 | N39: 08-2024
A40: 598090be | B40: 45555 | C40: 45463 | D40: otros | E40: 16665 | F40: 6 | G40: ARS | H40: Ropa y regalo | I40: Egreso | J40: No | K40: user-b | L40: 13.772727 | M40: 12.164234 | N40: 09-2024
A41: 598090be | B41: 45585 | C41: 45463 | D41: otros | E41: 16665 | F41: 6 | G41: ARS | H41: Ropa y regalo | I41: Egreso | J41: No | K41: user-b | L41: 14.618421 | M41: 12.164234 | N41: 10-2024
A42: 598090be | B42: 45616 | C42: 45463 | D42: otros | E42: 16665 | F42: 6 | G42: ARS | H42: Ropa y regalo | I42: Egreso | J42: No | K42: user-b | L42: 15.502326 | M42: 12.164234 | N42: 11-2024
A43: 0fb61cb0 | B43: 45463 | C43: 45463 | D43: super | E43: 32000 | F43: 1 | G43: ARS | I43: Egreso | J43: Si | K43: user-b | L43: 23.357664 | M43: 23.357664 | N43: 06-2024
A44: 03ed6348 | B44: 45464 | C44: 45464 | D44: auto | E44: 64000 | F44: 1 | G44: ARS | H44: Seguro | I44: Egreso | J44: Si | K44: user-b | L44: 46.715328 | M44: 46.715328 | N44: 06-2024
A45: 9512b155 | B45: 45464 | C45: 45464 | D45: salidas | E45: 46000 | F45: 1 | G45: ARS | I45: Egreso | J45: Si | K45: user-b | L45: 33.576642 | M45: 33.576642 | N45: 06-2024
A46: 9d6c1d28 | B46: 45465 | C46: 45465 | D46: otros | E46: 150 | F46: 1 | G46: USD | H46: joysticks | I46: Egreso | J46: No | K46: user-b | L46: 150 | M46: 150 | N46: 06-2024
A47: 46d5ddb2 | B47: 45465 | C47: 45465 | D47: otros | E47: 11 | F47: 1 | G47: USD | H47: Steam | I47: Egreso | J47: No | K47: user-b | L47: 11 | M47: 11 | N47: 06-2024
A48: a75d03e8 | B48: 45465 | C48: 45465 | D48: delivery | E48: 11000 | F48: 1 | G48: ARS | I48: Egreso | J48: Si | K48: user-b | L48: 8.0291971 | M48: 8.0291971 | N48: 06-2024
A49: 5dc0634c | B49: 45467 | C49: 45467 | D49: nafta | E49: 22000 | F49: 1 | G49: ARS | I49: Egreso | J49: Si | K49: user-b | L49: 16.058394 | M49: 16.058394 | N49: 06-2024
A50: 55adfa1b | B50: 45468 | C50: 45468 | D50: otros | E50: 12000 | F50: 3 | G50: ARS | H50: micro sd | I50: Egreso | J50: No | K50: user-b | L50: 8.7591241 | M50: 8.7591241 | N50: 06-2024
A51: 55adfa1b | B51: 45498 | C51: 45468 | D51: otros | E51: 12000 | F51: 3 | G51: ARS | H51: micro sd | I51: Egreso | J51: No | K51: user-b | L51: 9.2307692 | M51: 8.7591241 | N51: 07-2024
A52: 55adfa1b | B52: 45529 | C52: 45468 | D52: otros | E52: 12000 | F52: 3 | G52: ARS | H52: micro sd | I52: Egreso | J52: No | K52: user-b | L52: 9.7165992 | M52: 8.7591241 | N52: 08-2024
A53: 1c07f07c | B53: 45469 | C53: 45469 | D53: delivery | E53: 8000 | F53: 1 | G53: ARS | I53: Egreso | J53: Si | K53: user-b | L53: 5.8394161 | M53: 5.8394161 | N53: 06-2024
A54: f4f9ecd1 | B54: 45470 | C54: 45470 | D54: salidas | E54: 70000 | F54: 1 | G54: ARS | I54: Egreso | J54: Si | K54: user-b | L54: 51.094891 | M54: 51.094891 | N54: 06-2024
A55: ca631e01 | B55: 45471 | C55: 45471 | D55: delivery | E55: 14000 | F55: 1 | G55: ARS | I55: Egreso | J55: Si | K55: user-b | L55: 10.218978 | M55: 10.218978 | N55: 06-2024
A56: 7c6577c4 | B56: 45472 | C56: 45472 | D56: salidas | E56: 45000 | F56: 1 | G56: ARS | H56: Almuerzo floa | I56: Egreso | J56: Si | K56: user-b | L56: 32.846715 | M56: 32.846715 | N56: 06-2024
A57: 3308ceed | B57: 45472 | C57: 45472 | D57: salidas | E57: 40000 | F57: 1 | G57: ARS | I57: Egreso | J57: Si | K57: user-b | L57: 29.19708 | M57: 29.19708 | N57: 06-2024
A58: ea3dfdfd | B58: 45472 | C58: 45472 | D58: super | E58: 10000 | F58: 1 | G58: ARS | I58: Egreso | J58: Si | K58: user-b | L58: 7.2992701 | M58: 7.2992701 | N58: 06-2024
A59: bc488748 | B59: 45472 | C59: 45472 | D59: salidas | E59: 56000 | F59: 1 | G59: ARS | I59: Egreso | J59: Si | K59: user-b | L59: 40.875912 | M59: 40.875912 | N59: 06-2024
A60: e08fd082 | B60: 45474 | C60: 45474 | D60: super | E60: 1200 | F60: 1 | G60: ARS | I60: Egreso | J60: Si | K60: user-b | L60: 0.92307692 | M60: 0.92307692 | N60: 07-2024
A61: c88c2016-0a86-11f1-b3ca-325096b39f47 | B61: 45474 | C61: 45474 | D61: servicios | E61: 244 | F61: 1 | G61: USD | I61: Egreso | J61: Si | K61: user-b | L61: 244 | M61: 244 | N61: 07-2024
A62: 0034a018-0ab1-11f1-9ac3-325096b39f47 | B62: 45474 | C62: 45474 | D62: salario | E62: 1500 | F62: 1 | G62: USD | I62: Ingreso | J62: Si | K62: user-b | L62: 3750 | M62: 3750 | N62: 07-2024
A63: 0bad2316 | B63: 45475 | C63: 45475 | D63: salidas | E63: 73000 | F63: 1 | G63: ARS | H63: Nanum | I63: Egreso | J63: Si | K63: user-b | L63: 56.153846 | M63: 56.153846 | N63: 07-2024
A64: 8fae5122 | B64: 45475 | C64: 45475 | D64: delivery | E64: 5000 | F64: 1 | G64: ARS | I64: Egreso | J64: Si | K64: user-b | L64: 3.8461538 | M64: 3.8461538 | N64: 07-2024
A65: b269c650 | B65: 45475 | C65: 45475 | D65: super | E65: 20000 | F65: 1 | G65: ARS | I65: Egreso | J65: Si | K65: user-b | L65: 15.384615 | M65: 15.384615 | N65: 07-2024
A66: 7b3d6c53 | B66: 45476 | C66: 45476 | D66: otros | E66: 1915 | F66: 6 | G66: ARS | H66: Cargador celu | I66: Egreso | J66: No | K66: user-b | L66: 1.4730769 | M66: 1.4730769 | N66: 07-2024
A67: 7b3d6c53 | B67: 45507 | C67: 45476 | D67: otros | E67: 1915 | F67: 6 | G67: ARS | H67: Cargador celu | I67: Egreso | J67: No | K67: user-b | L67: 1.5506073 | M67: 1.4730769 | N67: 08-2024
A68: 7b3d6c53 | B68: 45538 | C68: 45476 | D68: otros | E68: 1915 | F68: 6 | G68: ARS | H68: Cargador celu | I68: Egreso | J68: No | K68: user-b | L68: 1.5826446 | M68: 1.4730769 | N68: 09-2024
A69: 7b3d6c53 | B69: 45568 | C69: 45476 | D69: otros | E69: 1915 | F69: 6 | G69: ARS | H69: Cargador celu | I69: Egreso | J69: No | K69: user-b | L69: 1.6798246 | M69: 1.4730769 | N69: 10-2024
A70: 7b3d6c53 | B70: 45599 | C70: 45476 | D70: otros | E70: 1915 | F70: 6 | G70: ARS | H70: Cargador celu | I70: Egreso | J70: No | K70: user-b | L70: 1.7813953 | M70: 1.4730769 | N70: 11-2024
A71: 7b3d6c53 | B71: 45629 | C71: 45476 | D71: otros | E71: 1915 | F71: 6 | G71: ARS | H71: Cargador celu | I71: Egreso | J71: No | K71: user-b | L71: 1.6652174 | M71: 1.4730769 | N71: 12-2024
A72: 2094c0cd | B72: 45477 | C72: 45477 | D72: delivery | E72: 17000 | F72: 1 | G72: ARS | I72: Egreso | J72: Si | K72: user-b | L72: 13.076923 | M72: 13.076923 | N72: 07-2024
A73: 193f55c0 | B73: 45478 | C73: 45478 | D73: super | E73: 27000 | F73: 1 | G73: ARS | I73: Egreso | J73: Si | K73: user-b | L73: 20.769231 | M73: 20.769231 | N73: 07-2024
A74: a429de0f | B74: 45479 | C74: 45479 | D74: delivery | E74: 9300 | F74: 1 | G74: ARS | I74: Egreso | J74: Si | K74: user-b | L74: 7.1538462 | M74: 7.1538462 | N74: 07-2024
A75: 29b8c40a | B75: 45479 | C75: 45479 | D75: salidas | E75: 5000 | F75: 3 | G75: ARS | I75: Egreso | J75: Si | K75: user-b | L75: 3.8461538 | M75: 3.8461538 | N75: 07-2024
A76: 29b8c40a | B76: 45510 | C76: 45479 | D76: salidas | E76: 5000 | F76: 3 | G76: ARS | I76: Egreso | J76: Si | K76: user-b | L76: 4.048583 | M76: 3.8461538 | N76: 08-2024
A77: 29b8c40a | B77: 45541 | C77: 45479 | D77: salidas | E77: 5000 | F77: 3 | G77: ARS | I77: Egreso | J77: Si | K77: user-b | L77: 4.1322314 | M77: 3.8461538 | N77: 09-2024
A78: 97d9c6f9 | B78: 45479 | C78: 45479 | D78: super | E78: 2000 | F78: 3 | G78: ARS | I78: Egreso | J78: Si | K78: user-b | L78: 1.5384615 | M78: 1.5384615 | N78: 07-2024
A79: 97d9c6f9 | B79: 45510 | C79: 45479 | D79: super | E79: 2000 | F79: 3 | G79: ARS | I79: Egreso | J79: Si | K79: user-b | L79: 1.6194332 | M79: 1.5384615 | N79: 08-2024
A80: 97d9c6f9 | B80: 45541 | C80: 45479 | D80: super | E80: 2000 | F80: 3 | G80: ARS | I80: Egreso | J80: Si | K80: user-b | L80: 1.6528926 | M80: 1.5384615 | N80: 09-2024
A81: 35a42b0b | B81: 45480 | C81: 45480 | D81: otros | E81: 1 | F81: 1 | G81: USD | H81: Android | I81: Egreso | J81: No | K81: user-b | L81: 1 | M81: 1 | N81: 07-2024
A82: a855b173 | B82: 45480 | C82: 45480 | D82: salidas | E82: 23000 | F82: 1 | G82: ARS | I82: Egreso | J82: Si | K82: user-b | L82: 17.692308 | M82: 17.692308 | N82: 07-2024
A83: cbcc13f9 | B83: 45482 | C83: 45482 | D83: salidas | E83: 32000 | F83: 1 | G83: ARS | I83: Egreso | J83: Si | K83: user-b | L83: 24.615385 | M83: 24.615385 | N83: 07-2024
A84: ffcdd5ac | B84: 45482 | C84: 45482 | D84: delivery | E84: 15000 | F84: 1 | G84: ARS | I84: Egreso | J84: Si | K84: user-b | L84: 11.538462 | M84: 11.538462 | N84: 07-2024
A85: 7040a3b2 | B85: 45482 | C85: 45482 | D85: super | E85: 38000 | F85: 3 | G85: ARS | I85: Egreso | J85: Si | K85: user-b | L85: 29.230769 | M85: 29.230769 | N85: 07-2024
A86: 7040a3b2 | B86: 45513 | C86: 45482 | D86: super | E86: 38000 | F86: 3 | G86: ARS | I86: Egreso | J86: Si | K86: user-b | L86: 30.769231 | M86: 29.230769 | N86: 08-2024
A87: 7040a3b2 | B87: 45544 | C87: 45482 | D87: super | E87: 38000 | F87: 3 | G87: ARS | I87: Egreso | J87: Si | K87: user-b | L87: 31.404959 | M87: 29.230769 | N87: 09-2024
A88: 20d9aee0 | B88: 45483 | C88: 45483 | D88: delivery | E88: 25500 | F88: 1 | G88: ARS | I88: Egreso | J88: Si | K88: user-b | L88: 19.615385 | M88: 19.615385 | N88: 07-2024
A89: 28e367aa | B89: 45483 | C89: 45483 | D89: otros | E89: 1935 | F89: 6 | G89: ARS | I89: Egreso | J89: No | K89: user-b | L89: 1.4884615 | M89: 1.4884615 | N89: 07-2024
A90: 28e367aa | B90: 45514 | C90: 45483 | D90: otros | E90: 1935 | F90: 6 | G90: ARS | I90: Egreso | J90: No | K90: user-b | L90: 1.5668016 | M90: 1.4884615 | N90: 08-2024
A91: 28e367aa | B91: 45545 | C91: 45483 | D91: otros | E91: 1935 | F91: 6 | G91: ARS | I91: Egreso | J91: No | K91: user-b | L91: 1.5991736 | M91: 1.4884615 | N91: 09-2024
A92: 28e367aa | B92: 45575 | C92: 45483 | D92: otros | E92: 1935 | F92: 6 | G92: ARS | I92: Egreso | J92: No | K92: user-b | L92: 1.6973684 | M92: 1.4884615 | N92: 10-2024
A93: 28e367aa | B93: 45606 | C93: 45483 | D93: otros | E93: 1935 | F93: 6 | G93: ARS | I93: Egreso | J93: No | K93: user-b | L93: 1.8 | M93: 1.4884615 | N93: 11-2024
... A95: 15a4d87d | B95: 45485 | C95: 45485 | D95: delivery | E95: 11000 | F95: 1 | G95: ARS | I95: Egreso | J95: Si | K95: user-b | L95: 8.4615385 | M95: 8.4615385 | N95: 07-2024
A96: 0c9a78ab | B96: 45486 | C96: 45486 | D96: otros | E96: 13000 | F96: 1 | G96: ARS | H96: Clases | I96: Egreso | J96: No | K96: user-b | L96: 10 | M96: 10 | N96: 07-2024
A97: 6dc272f0 | B97: 45486 | C97: 45486 | D97: super | E97: 12000 | F97: 1 | G97: ARS | I97: Egreso | J97: Si | K97: user-b | L97: 9.2307692 | M97: 9.2307692 | N97: 07-2024
A98: 8faed62b | B98: 45486 | C98: 45486 | D98: delivery | E98: 9000 | F98: 1 | G98: ARS | I98: Egreso | J98: Si | K98: user-b | L98: 6.9230769 | M98: 6.9230769 | N98: 07-2024
A99: a6cdee20 | B99: 45486 | C99: 45486 | D99: delivery | E99: 3000 | F99: 1 | G99: ARS | I99: Egreso | J99: Si | K99: user-b | L99: 2.3076923 | M99: 2.3076923 | N99: 07-2024
A100: 886144ce | B100: 45486 | C100: 45486 | D100: super | E100: 18000 | F100: 1 | G100: ARS | I100: Egreso | J100: Si | K100: user-b | L100: 13.846154 | M100: 13.846154 | N100: 07-2024
A101: 5ca39062 | B101: 45487 | C101: 45487 | D101: super | E101: 3330 | F101: 3 | G101: ARS | I101: Egreso | J101: Si | K101: user-b | L101: 2.5615385 | M101: 2.5615385 | N101: 07-2024
...

Sheet expenses-categories
A1: id | B1: nombre | C1: emoji | D1: type | E1: usuario
A2: cart | B2: super | C2: 🛒 | D2: Gasto | E2: shared
A3: other | B3: otros | C3: 🧦 | D3: Gasto | E3: shared
A4: car | B4: auto | C4: 🚙 | D4: Gasto | E4: shared
A5: holidays | B5: vacaciones | C5: 🌴 | D5: Gasto | E5: shared
A6: fuel | B6: nafta | C6: ⛽ | D6: Gasto | E6: shared
A7: delivery | B7: delivery | C7: 🍕 | D7: Gasto | E7: shared
A8: manteinance | B8: refaccion | C8: 🔧 | D8: Gasto | E8: shared
A9: taxes | B9: impuestos | C9: 📃 | D9: Gasto | E9: shared
A10: goingout | B10: salidas | C10: 🍷 | D10: Gasto | E10: shared
A11: medic | B11: salud | C11: ⚕️ | D11: Gasto | E11: shared
A12: utilities | B12: servicios | C12: 🏠 | D12: Gasto | E12: shared
... A19: pets | B19: perros | C19: 🐕 | D19: Gasto | E19: shared

Sheet exchange
A1: period | B1: usd | C1: eur
A2: 45383 | B2: 1030 | C2: 0.84
A3: 45413 | B3: 1279 | C3: 0.84
A4: 45444 | B4: 1370 | C4: 0.84
A5: 45474 | B5: 1300 | C5: 0.84
A6: 45505 | B6: 1235 | C6: 0.84
A7: 45536 | B7: 1210 | C7: 0.84
A8: 45566 | B8: 1140 | C8: 0.84
A9: 45597 | B9: 1075 | C9: 0.84
A10: 45627 | B10: 1150 | C10: 0.84
A11: 45658 | B11: 1160 | C11: 0.84
A12: 45689 | B12: 1200 | C12: 0.84
A13: 45717 | B13: 1300 | C13: 0.84
... A30: 46235 | B30: 1510 | C30: 0.88

Sheet habits
A1: day | B1: training | C1: dont-smoke | D1: dont-scroll | E1: user
A2: 46251 | B2: FALSE | C2: FALSE | D2: FALSE | E2: user-b
A3: 46252 | B3: TRUE | C3: TRUE | D3: FALSE | E3: user-b
A4: 46253 | B4: FALSE | C4: FALSE | D4: FALSE | E4: user-b
A5: 46254 | B5: TRUE | C5: TRUE | D5: FALSE | E5: user-b
A6: 46256 | B6: FALSE | C6: TRUE | D6: FALSE | E6: user-b

Sheet habits-categories
A1: id | B1: nombre | C1: emoji | D1: default | E1: user
A2: training | B2: Entrenamiento | C2: 🏋️‍♂️ | D2: FALSE | E2: user-b
A3: dont-smoke | B3: No fumar | C3: 🚭 | D3: TRUE | E3: user-b
A4: dont-scroll | B4: Celu Detox | C4: 📵 | D4: FALSE | E4: user-b
